manojksum/__init__.py
manojksum-0.0.1.dist-info/METADATA
manojksum-0.0.1.dist-info/RECORD
manojksum-0.0.1.dist-info/WHEEL
manojksum-0.0.1.dist-info/top_level.txt
